{"wallet":"0x6f9410cef448e7c96c224700c3fd8017363578d4","rank":804689,"lifetime":{"months_active":7,"first":"2023-07","last":"2025-10","tx_sum":169,"uniq_sum":54,"trade_sum":7,"nft_sum":0,"gas_sum":0.00118,"avg_balance_eth_mean":0.001356,"streak_best_days":3,"gas_sum_filled":0.00118},"months":{"2023-07":{"txs":0,"uniq":0,"trade":0,"nft":0,"gas":0,"bal":0,"days":0,"spread":0,"streak":0,"rank_m":552947,"pct_m":0.587902},"2023-08":{"txs":0,"uniq":0,"trade":0,"nft":0,"gas":0,"bal":0,"days":0,"spread":0,"streak":0,"rank_m":603147,"pct_m":0.641276},"2023-09":{"txs":0,"uniq":0,"trade":0,"nft":0,"gas":0,"bal":0,"days":0,"spread":0,"streak":0,"rank_m":616552,"pct_m":0.655528},"2023-10":{"txs":0,"uniq":0,"trade":0,"nft":0,"gas":0,"bal":0,"days":0,"spread":0,"streak":0,"rank_m":627401,"pct_m":0.667063},"2023-11":{"txs":0,"uniq":0,"trade":0,"nft":0,"gas":0,"bal":0,"days":0,"spread":0,"streak":0,"rank_m":637006,"pct_m":0.677275},"2023-12":{"txs":0,"uniq":0,"trade":0,"nft":0,"gas":0,"bal":0,"days":0,"spread":0,"streak":0,"rank_m":648568,"pct_m":0.689568},"2024-01":{"txs":0,"uniq":0,"trade":0,"nft":0,"gas":0,"bal":0,"days":0,"spread":0,"streak":0,"rank_m":658876,"pct_m":0.700528},"2024-02":{"txs":0,"uniq":0,"trade":0,"nft":0,"gas":0,"bal":0,"days":0,"spread":0,"streak":0,"rank_m":681118,"pct_m":0.724176},"2024-03":{"txs":0,"uniq":0,"trade":0,"nft":0,"gas":0,"bal":0,"days":0,"spread":0,"streak":0,"rank_m":717179,"pct_m":0.762516},"2024-04":{"txs":0,"uniq":0,"trade":0,"nft":0,"gas":0,"bal":0,"days":0,"spread":0,"streak":0,"rank_m":751757,"pct_m":0.79928},"2024-05":{"txs":0,"uniq":0,"trade":0,"nft":0,"gas":0,"bal":0,"days":0,"spread":0,"streak":0,"rank_m":770668,"pct_m":0.819387},"2024-06":{"txs":0,"uniq":0,"trade":0,"nft":0,"gas":0,"bal":0,"days":0,"spread":0,"streak":0,"rank_m":786830,"pct_m":0.836571},"2024-07":{"txs":0,"uniq":0,"trade":0,"nft":0,"gas":0,"bal":0,"days":0,"spread":0,"streak":0,"rank_m":800096,"pct_m":0.850675},"2024-08":{"txs":0,"uniq":0,"trade":0,"nft":0,"gas":0,"bal":0,"days":0,"spread":0,"streak":0,"rank_m":811429,"pct_m":0.862725},"2024-09":{"txs":0,"uniq":0,"trade":0,"nft":0,"gas":0,"bal":0,"days":0,"spread":0,"streak":0,"rank_m":820674,"pct_m":0.872554},"2024-10":{"txs":0,"uniq":0,"trade":0,"nft":0,"gas":0,"bal":0,"days":0,"spread":0,"streak":0,"rank_m":833217,"pct_m":0.88589},"2024-11":{"txs":0,"uniq":0,"trade":0,"nft":0,"gas":0,"bal":0,"days":0,"spread":0,"streak":0,"rank_m":843965,"pct_m":0.897318},"2024-12":{"txs":0,"uniq":0,"trade":0,"nft":0,"gas":0,"bal":0,"days":0,"spread":0,"streak":0,"rank_m":858090,"pct_m":0.912336},"2025-01":{"txs":0,"uniq":0,"trade":0,"nft":0,"gas":0,"bal":0,"days":0,"spread":0,"streak":0,"rank_m":870591,"pct_m":0.925627},"2025-02":{"txs":0,"uniq":0,"trade":0,"nft":0,"gas":0,"bal":0,"days":0,"spread":0,"streak":0,"rank_m":883815,"pct_m":0.939687},"2025-03":{"txs":0,"uniq":0,"trade":0,"nft":0,"gas":0,"bal":0,"days":0,"spread":0,"streak":0,"rank_m":896068,"pct_m":0.952714},"2025-04":{"txs":3,"uniq":2,"trade":0,"nft":0,"gas":0.000012,"bal":0.000106,"days":2,"spread":0.066667,"streak":2,"rank_m":478488,"pct_m":0.508736,"gas_method":"exact"},"2025-05":{"txs":5,"uniq":3,"trade":0,"nft":0,"gas":0.000035,"bal":0.001375,"days":1,"spread":0.032258,"streak":1,"rank_m":434181,"pct_m":0.461628,"gas_method":"estimated"},"2025-06":{"txs":37,"uniq":15,"trade":1,"nft":0,"gas":0.00026,"bal":0.005282,"days":12,"spread":0.4,"streak":3,"rank_m":95209,"pct_m":0.101227,"gas_method":"estimated"},"2025-07":{"txs":36,"uniq":12,"trade":0,"nft":0,"gas":0.000253,"bal":0.008858,"days":10,"spread":0.322581,"streak":2,"rank_m":133539,"pct_m":0.14198,"gas_method":"estimated"},"2025-08":{"txs":49,"uniq":14,"trade":6,"nft":0,"gas":0.000345,"bal":0.008373,"days":11,"spread":0.354839,"streak":2,"rank_m":50331,"pct_m":0.053512,"gas_method":"estimated"},"2025-09":{"txs":24,"uniq":7,"trade":0,"nft":0,"gas":0.000169,"bal":0.007435,"days":5,"spread":0.166667,"streak":1,"rank_m":214269,"pct_m":0.227814,"gas_method":"estimated"},"2025-10":{"txs":15,"uniq":1,"trade":0,"nft":0,"gas":0.000106,"bal":0.006548,"days":5,"spread":0.16129,"streak":1,"rank_m":183802,"pct_m":0.195421,"gas_method":"estimated"}}}