{"wallet":"0x67c6c55b3d5f66bd76f822bc0ae46a6f84623421","rank":509754,"lifetime":{"months_active":11,"first":"2023-07","last":"2025-10","tx_sum":115,"uniq_sum":69,"trade_sum":5,"nft_sum":25,"gas_sum":0.007632,"avg_balance_eth_mean":0.015002,"streak_best_days":3,"gas_sum_filled":0.007632},"months":{"2023-07":{"txs":0,"uniq":0,"trade":0,"nft":0,"gas":0,"bal":0,"days":0,"spread":0,"streak":0,"rank_m":580163,"pct_m":0.616839},"2023-08":{"txs":1,"uniq":1,"trade":0,"nft":0,"gas":0.000667,"bal":0.000391,"days":1,"spread":0.032258,"streak":1,"rank_m":146044,"pct_m":0.155276,"gas_method":"exact"},"2023-09":{"txs":0,"uniq":0,"trade":0,"nft":0,"gas":0,"bal":0.000391,"days":0,"spread":0,"streak":0,"rank_m":288969,"pct_m":0.307236},"2023-10":{"txs":0,"uniq":0,"trade":0,"nft":0,"gas":0,"bal":0.000391,"days":0,"spread":0,"streak":0,"rank_m":302619,"pct_m":0.321749},"2023-11":{"txs":0,"uniq":0,"trade":0,"nft":0,"gas":0,"bal":0.000391,"days":0,"spread":0,"streak":0,"rank_m":313761,"pct_m":0.333595},"2023-12":{"txs":1,"uniq":1,"trade":0,"nft":0,"gas":0.000224,"bal":0.000217,"days":1,"spread":0.032258,"streak":1,"rank_m":193139,"pct_m":0.205348,"gas_method":"estimated"},"2024-01":{"txs":3,"uniq":3,"trade":0,"nft":1,"gas":0.000627,"bal":0.003778,"days":1,"spread":0.032258,"streak":1,"rank_m":130501,"pct_m":0.13875,"gas_method":"estimated"},"2024-02":{"txs":31,"uniq":14,"trade":0,"nft":5,"gas":0.003657,"bal":0.014072,"days":11,"spread":0.37931,"streak":3,"rank_m":24242,"pct_m":0.025773,"gas_method":"estimated"},"2024-03":{"txs":29,"uniq":18,"trade":2,"nft":10,"gas":0.00198,"bal":0.032978,"days":5,"spread":0.16129,"streak":2,"rank_m":43571,"pct_m":0.046324,"gas_method":"exact"},"2024-04":{"txs":17,"uniq":10,"trade":2,"nft":6,"gas":0.000371,"bal":0.096425,"days":8,"spread":0.266667,"streak":1,"rank_m":133152,"pct_m":0.141569,"gas_method":"estimated"},"2024-05":{"txs":8,"uniq":4,"trade":1,"nft":2,"gas":0.000058,"bal":0.055254,"days":4,"spread":0.129032,"streak":2,"rank_m":169821,"pct_m":0.180556,"gas_method":"estimated"},"2024-06":{"txs":8,"uniq":4,"trade":0,"nft":1,"gas":0.000002,"bal":0.056561,"days":5,"spread":0.166667,"streak":2,"rank_m":173613,"pct_m":0.184587,"gas_method":"estimated"},"2024-07":{"txs":9,"uniq":8,"trade":0,"nft":0,"gas":0.00001,"bal":0.018043,"days":2,"spread":0.064516,"streak":1,"rank_m":243104,"pct_m":0.258471,"gas_method":"estimated"},"2024-08":{"txs":0,"uniq":0,"trade":0,"nft":0,"gas":0,"bal":0.018043,"days":0,"spread":0,"streak":0,"rank_m":494766,"pct_m":0.526043},"2024-09":{"txs":1,"uniq":1,"trade":0,"nft":0,"gas":0,"bal":0.017589,"days":1,"spread":0.033333,"streak":1,"rank_m":327808,"pct_m":0.34853,"gas_method":"estimated"},"2024-10":{"txs":0,"uniq":0,"trade":0,"nft":0,"gas":0,"bal":0.017589,"days":0,"spread":0,"streak":0,"rank_m":507341,"pct_m":0.539413},"2024-11":{"txs":0,"uniq":0,"trade":0,"nft":0,"gas":0,"bal":0.017589,"days":0,"spread":0,"streak":0,"rank_m":542368,"pct_m":0.576654},"2024-12":{"txs":0,"uniq":0,"trade":0,"nft":0,"gas":0,"bal":0.017589,"days":0,"spread":0,"streak":0,"rank_m":599970,"pct_m":0.637898},"2025-01":{"txs":0,"uniq":0,"trade":0,"nft":0,"gas":0,"bal":0.017589,"days":0,"spread":0,"streak":0,"rank_m":585273,"pct_m":0.622272},"2025-02":{"txs":0,"uniq":0,"trade":0,"nft":0,"gas":0,"bal":0.017589,"days":0,"spread":0,"streak":0,"rank_m":581005,"pct_m":0.617734},"2025-03":{"txs":0,"uniq":0,"trade":0,"nft":0,"gas":0,"bal":0.017589,"days":0,"spread":0,"streak":0,"rank_m":562894,"pct_m":0.598478},"2025-04":{"txs":7,"uniq":5,"trade":0,"nft":0,"gas":0.000036,"bal":0,"days":1,"spread":0.033333,"streak":1,"rank_m":472489,"pct_m":0.502358,"gas_method":"exact"},"2025-05":{"txs":0,"uniq":0,"trade":0,"nft":0,"gas":0,"bal":0,"days":0,"spread":0,"streak":0,"rank_m":903431,"pct_m":0.960543},"2025-06":{"txs":0,"uniq":0,"trade":0,"nft":0,"gas":0,"bal":0,"days":0,"spread":0,"streak":0,"rank_m":914160,"pct_m":0.97195},"2025-07":{"txs":0,"uniq":0,"trade":0,"nft":0,"gas":0,"bal":0,"days":0,"spread":0,"streak":0,"rank_m":925265,"pct_m":0.983757},"2025-08":{"txs":0,"uniq":0,"trade":0,"nft":0,"gas":0,"bal":0,"days":0,"spread":0,"streak":0,"rank_m":928233,"pct_m":0.986913},"2025-09":{"txs":0,"uniq":0,"trade":0,"nft":0,"gas":0,"bal":0,"days":0,"spread":0,"streak":0,"rank_m":928827,"pct_m":0.987544},"2025-10":{"txs":0,"uniq":0,"trade":0,"nft":0,"gas":0,"bal":0,"days":0,"spread":0,"streak":0,"rank_m":921617,"pct_m":0.979879}}}