{"wallet":"0x6e01ed4e5d66fd051a21572df7cebd87eb5a83b3","rank":536547,"lifetime":{"months_active":12,"first":"2023-07","last":"2025-10","tx_sum":188,"uniq_sum":171,"trade_sum":0,"nft_sum":143,"gas_sum":0.000229,"avg_balance_eth_mean":0.000092,"streak_best_days":29,"gas_sum_filled":0.000229},"months":{"2023-07":{"txs":0,"uniq":0,"trade":0,"nft":0,"gas":0,"bal":0,"days":0,"spread":0,"streak":0,"rank_m":558326,"pct_m":0.593621},"2023-08":{"txs":0,"uniq":0,"trade":0,"nft":0,"gas":0,"bal":0,"days":0,"spread":0,"streak":0,"rank_m":607814,"pct_m":0.646238},"2023-09":{"txs":0,"uniq":0,"trade":0,"nft":0,"gas":0,"bal":0,"days":0,"spread":0,"streak":0,"rank_m":621048,"pct_m":0.660308},"2023-10":{"txs":0,"uniq":0,"trade":0,"nft":0,"gas":0,"bal":0,"days":0,"spread":0,"streak":0,"rank_m":631735,"pct_m":0.671671},"2023-11":{"txs":0,"uniq":0,"trade":0,"nft":0,"gas":0,"bal":0,"days":0,"spread":0,"streak":0,"rank_m":641207,"pct_m":0.681742},"2023-12":{"txs":0,"uniq":0,"trade":0,"nft":0,"gas":0,"bal":0,"days":0,"spread":0,"streak":0,"rank_m":652603,"pct_m":0.693858},"2024-01":{"txs":0,"uniq":0,"trade":0,"nft":0,"gas":0,"bal":0,"days":0,"spread":0,"streak":0,"rank_m":662761,"pct_m":0.704658},"2024-02":{"txs":0,"uniq":0,"trade":0,"nft":0,"gas":0,"bal":0,"days":0,"spread":0,"streak":0,"rank_m":684672,"pct_m":0.727954},"2024-03":{"txs":0,"uniq":0,"trade":0,"nft":0,"gas":0,"bal":0,"days":0,"spread":0,"streak":0,"rank_m":720242,"pct_m":0.765773},"2024-04":{"txs":3,"uniq":2,"trade":0,"nft":1,"gas":0.000007,"bal":0.000005,"days":1,"spread":0.033333,"streak":1,"rank_m":453742,"pct_m":0.482426,"gas_method":"estimated"},"2024-05":{"txs":1,"uniq":1,"trade":0,"nft":1,"gas":0.000001,"bal":0.000023,"days":1,"spread":0.032258,"streak":1,"rank_m":482454,"pct_m":0.512953,"gas_method":"estimated"},"2024-06":{"txs":0,"uniq":0,"trade":0,"nft":0,"gas":0,"bal":0.000023,"days":0,"spread":0,"streak":0,"rank_m":632068,"pct_m":0.672025},"2024-07":{"txs":4,"uniq":3,"trade":0,"nft":3,"gas":0,"bal":0.000017,"days":3,"spread":0.096774,"streak":2,"rank_m":407080,"pct_m":0.432814,"gas_method":"estimated"},"2024-08":{"txs":10,"uniq":8,"trade":0,"nft":8,"gas":0.000001,"bal":0.000089,"days":9,"spread":0.290323,"streak":2,"rank_m":327508,"pct_m":0.348211,"gas_method":"estimated"},"2024-09":{"txs":19,"uniq":14,"trade":0,"nft":14,"gas":0,"bal":0.000381,"days":8,"spread":0.266667,"streak":5,"rank_m":108223,"pct_m":0.115064,"gas_method":"exact"},"2024-10":{"txs":112,"uniq":104,"trade":0,"nft":107,"gas":0.000007,"bal":0.000364,"days":21,"spread":0.677419,"streak":15,"rank_m":120228,"pct_m":0.127827,"gas_method":"estimated"},"2024-11":{"txs":29,"uniq":29,"trade":0,"nft":8,"gas":0.000067,"bal":0.000239,"days":23,"spread":0.766667,"streak":14,"rank_m":118617,"pct_m":0.126115,"gas_method":"exact"},"2024-12":{"txs":5,"uniq":5,"trade":0,"nft":0,"gas":0.00011,"bal":0.000168,"days":5,"spread":0.16129,"streak":2,"rank_m":433748,"pct_m":0.461168,"gas_method":"exact"},"2025-01":{"txs":0,"uniq":0,"trade":0,"nft":0,"gas":0,"bal":0.000168,"days":0,"spread":0,"streak":0,"rank_m":726470,"pct_m":0.772395},"2025-02":{"txs":1,"uniq":1,"trade":0,"nft":0,"gas":0.000007,"bal":0.000163,"days":1,"spread":0.035714,"streak":1,"rank_m":552001,"pct_m":0.586896,"gas_method":"exact"},"2025-03":{"txs":1,"uniq":1,"trade":0,"nft":0,"gas":0.000008,"bal":0.000152,"days":1,"spread":0.032258,"streak":1,"rank_m":517141,"pct_m":0.549832,"gas_method":"exact"},"2025-04":{"txs":0,"uniq":0,"trade":0,"nft":0,"gas":0,"bal":0.000152,"days":0,"spread":0,"streak":0,"rank_m":788878,"pct_m":0.838748},"2025-05":{"txs":1,"uniq":1,"trade":0,"nft":0,"gas":0.000007,"bal":0.000112,"days":1,"spread":0.032258,"streak":1,"rank_m":652073,"pct_m":0.693295,"gas_method":"estimated"},"2025-06":{"txs":0,"uniq":0,"trade":0,"nft":0,"gas":0,"bal":0.000112,"days":0,"spread":0,"streak":0,"rank_m":827746,"pct_m":0.880073},"2025-07":{"txs":0,"uniq":0,"trade":0,"nft":0,"gas":0,"bal":0.000112,"days":0,"spread":0,"streak":0,"rank_m":850060,"pct_m":0.903798},"2025-08":{"txs":2,"uniq":2,"trade":0,"nft":1,"gas":0.000014,"bal":0.000102,"days":2,"spread":0.064516,"streak":1,"rank_m":523095,"pct_m":0.556163,"gas_method":"estimated"},"2025-09":{"txs":0,"uniq":0,"trade":0,"nft":0,"gas":0,"bal":0.000102,"days":0,"spread":0,"streak":0,"rank_m":844597,"pct_m":0.89799},"2025-10":{"txs":0,"uniq":0,"trade":0,"nft":0,"gas":0,"bal":0.000102,"days":0,"spread":0,"streak":0,"rank_m":813519,"pct_m":0.864947}}}