{"wallet":"0x6e7693c6a746401e9bab53b010ee9988569bf85b","rank":28393,"lifetime":{"months_active":12,"first":"2023-07","last":"2025-10","tx_sum":3111,"uniq_sum":1043,"trade_sum":7,"nft_sum":7,"gas_sum":0.015593,"avg_balance_eth_mean":0.163006,"streak_best_days":32,"gas_sum_filled":0.015593},"months":{"2023-07":{"txs":0,"uniq":0,"trade":0,"nft":0,"gas":0,"bal":0,"days":0,"spread":0,"streak":0,"rank_m":556743,"pct_m":0.591938},"2023-08":{"txs":0,"uniq":0,"trade":0,"nft":0,"gas":0,"bal":0,"days":0,"spread":0,"streak":0,"rank_m":606419,"pct_m":0.644754},"2023-09":{"txs":0,"uniq":0,"trade":0,"nft":0,"gas":0,"bal":0,"days":0,"spread":0,"streak":0,"rank_m":619704,"pct_m":0.658879},"2023-10":{"txs":0,"uniq":0,"trade":0,"nft":0,"gas":0,"bal":0,"days":0,"spread":0,"streak":0,"rank_m":630439,"pct_m":0.670293},"2023-11":{"txs":0,"uniq":0,"trade":0,"nft":0,"gas":0,"bal":0,"days":0,"spread":0,"streak":0,"rank_m":639951,"pct_m":0.680406},"2023-12":{"txs":0,"uniq":0,"trade":0,"nft":0,"gas":0,"bal":0,"days":0,"spread":0,"streak":0,"rank_m":651399,"pct_m":0.692578},"2024-01":{"txs":0,"uniq":0,"trade":0,"nft":0,"gas":0,"bal":0,"days":0,"spread":0,"streak":0,"rank_m":661602,"pct_m":0.703426},"2024-02":{"txs":0,"uniq":0,"trade":0,"nft":0,"gas":0,"bal":0,"days":0,"spread":0,"streak":0,"rank_m":683602,"pct_m":0.726817},"2024-03":{"txs":1232,"uniq":367,"trade":1,"nft":6,"gas":0.007241,"bal":0.107865,"days":30,"spread":0.967742,"streak":30,"rank_m":1048,"pct_m":0.001113,"gas_method":"exact"},"2024-04":{"txs":38,"uniq":17,"trade":0,"nft":1,"gas":0.005477,"bal":0.051836,"days":9,"spread":0.3,"streak":5,"rank_m":70314,"pct_m":0.074758,"gas_method":"exact"},"2024-05":{"txs":0,"uniq":0,"trade":0,"nft":0,"gas":0,"bal":0.051836,"days":0,"spread":0,"streak":0,"rank_m":461692,"pct_m":0.490878},"2024-06":{"txs":4,"uniq":3,"trade":0,"nft":0,"gas":0,"bal":0.017034,"days":1,"spread":0.033333,"streak":1,"rank_m":342216,"pct_m":0.363849,"gas_method":"estimated"},"2024-07":{"txs":1,"uniq":0,"trade":0,"nft":0,"gas":0,"bal":0.032755,"days":1,"spread":0.032258,"streak":1,"rank_m":366709,"pct_m":0.38989,"gas_method":"estimated"},"2024-08":{"txs":0,"uniq":0,"trade":0,"nft":0,"gas":0,"bal":0.032755,"days":0,"spread":0,"streak":0,"rank_m":477925,"pct_m":0.508137},"2024-09":{"txs":0,"uniq":0,"trade":0,"nft":0,"gas":0,"bal":0.032755,"days":0,"spread":0,"streak":0,"rank_m":444469,"pct_m":0.472566},"2024-10":{"txs":0,"uniq":0,"trade":0,"nft":0,"gas":0,"bal":0.032755,"days":0,"spread":0,"streak":0,"rank_m":487446,"pct_m":0.51826},"2024-11":{"txs":183,"uniq":59,"trade":0,"nft":0,"gas":0.000421,"bal":0.03046,"days":11,"spread":0.366667,"streak":5,"rank_m":25261,"pct_m":0.026857,"gas_method":"exact"},"2024-12":{"txs":897,"uniq":275,"trade":0,"nft":0,"gas":0.000007,"bal":0.134277,"days":30,"spread":0.967742,"streak":24,"rank_m":84947,"pct_m":0.090316,"gas_method":"exact"},"2025-01":{"txs":419,"uniq":182,"trade":0,"nft":0,"gas":0.000075,"bal":0.46078,"days":19,"spread":0.612903,"streak":10,"rank_m":50249,"pct_m":0.053425,"gas_method":"exact"},"2025-02":{"txs":0,"uniq":0,"trade":0,"nft":0,"gas":0,"bal":0.46078,"days":0,"spread":0,"streak":0,"rank_m":531013,"pct_m":0.564581},"2025-03":{"txs":0,"uniq":0,"trade":0,"nft":0,"gas":0,"bal":0.46078,"days":0,"spread":0,"streak":0,"rank_m":503509,"pct_m":0.535339},"2025-04":{"txs":0,"uniq":0,"trade":0,"nft":0,"gas":0,"bal":0.46078,"days":0,"spread":0,"streak":0,"rank_m":543446,"pct_m":0.5778},"2025-05":{"txs":27,"uniq":12,"trade":0,"nft":0,"gas":0.00019,"bal":0.386879,"days":5,"spread":0.16129,"streak":3,"rank_m":26041,"pct_m":0.027686,"gas_method":"estimated"},"2025-06":{"txs":122,"uniq":48,"trade":2,"nft":0,"gas":0.000859,"bal":0.24068,"days":8,"spread":0.266667,"streak":7,"rank_m":7182,"pct_m":0.007635,"gas_method":"estimated"},"2025-07":{"txs":184,"uniq":77,"trade":4,"nft":0,"gas":0.001295,"bal":0.477406,"days":15,"spread":0.483871,"streak":6,"rank_m":2054,"pct_m":0.002183,"gas_method":"estimated"},"2025-08":{"txs":2,"uniq":2,"trade":0,"nft":0,"gas":0.000014,"bal":0.418039,"days":2,"spread":0.064516,"streak":1,"rank_m":203044,"pct_m":0.215879,"gas_method":"estimated"},"2025-09":{"txs":0,"uniq":0,"trade":0,"nft":0,"gas":0,"bal":0.418039,"days":0,"spread":0,"streak":0,"rank_m":386952,"pct_m":0.411413},"2025-10":{"txs":2,"uniq":1,"trade":0,"nft":0,"gas":0.000014,"bal":0.255672,"days":2,"spread":0.064516,"streak":1,"rank_m":109629,"pct_m":0.116558,"gas_method":"estimated"}}}