{"wallet":"0x6ec46c36c5fb4b41ce1e114605e6205c03563123","rank":385777,"lifetime":{"months_active":12,"first":"2023-07","last":"2025-10","tx_sum":299,"uniq_sum":144,"trade_sum":2,"nft_sum":1,"gas_sum":0.00354,"avg_balance_eth_mean":0.000062,"streak_best_days":9,"gas_sum_filled":0.00354},"months":{"2023-07":{"txs":0,"uniq":0,"trade":0,"nft":0,"gas":0,"bal":0,"days":0,"spread":0,"streak":0,"rank_m":555681,"pct_m":0.590809},"2023-08":{"txs":0,"uniq":0,"trade":0,"nft":0,"gas":0,"bal":0,"days":0,"spread":0,"streak":0,"rank_m":605486,"pct_m":0.643762},"2023-09":{"txs":0,"uniq":0,"trade":0,"nft":0,"gas":0,"bal":0,"days":0,"spread":0,"streak":0,"rank_m":618807,"pct_m":0.657926},"2023-10":{"txs":0,"uniq":0,"trade":0,"nft":0,"gas":0,"bal":0,"days":0,"spread":0,"streak":0,"rank_m":629575,"pct_m":0.669374},"2023-11":{"txs":0,"uniq":0,"trade":0,"nft":0,"gas":0,"bal":0,"days":0,"spread":0,"streak":0,"rank_m":639111,"pct_m":0.679513},"2023-12":{"txs":0,"uniq":0,"trade":0,"nft":0,"gas":0,"bal":0,"days":0,"spread":0,"streak":0,"rank_m":650595,"pct_m":0.691723},"2024-01":{"txs":0,"uniq":0,"trade":0,"nft":0,"gas":0,"bal":0,"days":0,"spread":0,"streak":0,"rank_m":660837,"pct_m":0.702613},"2024-02":{"txs":0,"uniq":0,"trade":0,"nft":0,"gas":0,"bal":0,"days":0,"spread":0,"streak":0,"rank_m":682909,"pct_m":0.72608},"2024-03":{"txs":0,"uniq":0,"trade":0,"nft":0,"gas":0,"bal":0,"days":0,"spread":0,"streak":0,"rank_m":718733,"pct_m":0.764169},"2024-04":{"txs":0,"uniq":0,"trade":0,"nft":0,"gas":0,"bal":0,"days":0,"spread":0,"streak":0,"rank_m":753048,"pct_m":0.800653},"2024-05":{"txs":0,"uniq":0,"trade":0,"nft":0,"gas":0,"bal":0,"days":0,"spread":0,"streak":0,"rank_m":771851,"pct_m":0.820645},"2024-06":{"txs":0,"uniq":0,"trade":0,"nft":0,"gas":0,"bal":0,"days":0,"spread":0,"streak":0,"rank_m":787914,"pct_m":0.837723},"2024-07":{"txs":0,"uniq":0,"trade":0,"nft":0,"gas":0,"bal":0,"days":0,"spread":0,"streak":0,"rank_m":801091,"pct_m":0.851733},"2024-08":{"txs":0,"uniq":0,"trade":0,"nft":0,"gas":0,"bal":0,"days":0,"spread":0,"streak":0,"rank_m":812360,"pct_m":0.863715},"2024-09":{"txs":0,"uniq":0,"trade":0,"nft":0,"gas":0,"bal":0,"days":0,"spread":0,"streak":0,"rank_m":821541,"pct_m":0.873476},"2024-10":{"txs":20,"uniq":6,"trade":0,"nft":1,"gas":0.000001,"bal":0.000051,"days":8,"spread":0.258065,"streak":3,"rank_m":355636,"pct_m":0.378117,"gas_method":"estimated"},"2024-11":{"txs":83,"uniq":2,"trade":0,"nft":0,"gas":0.000189,"bal":0.000101,"days":17,"spread":0.566667,"streak":9,"rank_m":200839,"pct_m":0.213535,"gas_method":"exact"},"2024-12":{"txs":1,"uniq":1,"trade":0,"nft":0,"gas":0.000022,"bal":0.00008,"days":1,"spread":0.032258,"streak":1,"rank_m":595946,"pct_m":0.633619,"gas_method":"exact"},"2025-01":{"txs":109,"uniq":105,"trade":0,"nft":0,"gas":0.002754,"bal":0.000808,"days":5,"spread":0.16129,"streak":2,"rank_m":131018,"pct_m":0.1393,"gas_method":"exact"},"2025-02":{"txs":7,"uniq":5,"trade":0,"nft":0,"gas":0.000035,"bal":0.000064,"days":5,"spread":0.178571,"streak":2,"rank_m":359622,"pct_m":0.382355,"gas_method":"exact"},"2025-03":{"txs":0,"uniq":0,"trade":0,"nft":0,"gas":0,"bal":0.000064,"days":0,"spread":0,"streak":0,"rank_m":799085,"pct_m":0.8496},"2025-04":{"txs":4,"uniq":1,"trade":0,"nft":0,"gas":0.000012,"bal":0.000131,"days":3,"spread":0.1,"streak":2,"rank_m":464697,"pct_m":0.494073,"gas_method":"exact"},"2025-05":{"txs":9,"uniq":3,"trade":0,"nft":0,"gas":0.000063,"bal":0.000032,"days":4,"spread":0.129032,"streak":2,"rank_m":550199,"pct_m":0.58498,"gas_method":"estimated"},"2025-06":{"txs":22,"uniq":8,"trade":2,"nft":0,"gas":0.000155,"bal":0.000001,"days":5,"spread":0.166667,"streak":1,"rank_m":462478,"pct_m":0.491714,"gas_method":"estimated"},"2025-07":{"txs":14,"uniq":5,"trade":0,"nft":0,"gas":0.000099,"bal":0.000098,"days":5,"spread":0.16129,"streak":1,"rank_m":554093,"pct_m":0.589121,"gas_method":"estimated"},"2025-08":{"txs":5,"uniq":4,"trade":0,"nft":0,"gas":0.000035,"bal":0.000055,"days":4,"spread":0.129032,"streak":2,"rank_m":568339,"pct_m":0.604267,"gas_method":"estimated"},"2025-09":{"txs":13,"uniq":2,"trade":0,"nft":0,"gas":0.000091,"bal":0.000176,"days":5,"spread":0.166667,"streak":2,"rank_m":496863,"pct_m":0.528273,"gas_method":"estimated"},"2025-10":{"txs":12,"uniq":2,"trade":0,"nft":0,"gas":0.000084,"bal":0.00007,"days":3,"spread":0.096774,"streak":1,"rank_m":460792,"pct_m":0.489921,"gas_method":"estimated"}}}