{"wallet":"0x6d54011b0513065e20cbe8a2f1dbc1b596449b87","rank":885638,"lifetime":{"months_active":6,"first":"2023-07","last":"2025-10","tx_sum":171,"uniq_sum":47,"trade_sum":0,"nft_sum":1,"gas_sum":0.001204,"avg_balance_eth_mean":0.001209,"streak_best_days":4,"gas_sum_filled":0.001204},"months":{"2023-07":{"txs":0,"uniq":0,"trade":0,"nft":0,"gas":0,"bal":0,"days":0,"spread":0,"streak":0,"rank_m":560685,"pct_m":0.596129},"2023-08":{"txs":0,"uniq":0,"trade":0,"nft":0,"gas":0,"bal":0,"days":0,"spread":0,"streak":0,"rank_m":609879,"pct_m":0.648433},"2023-09":{"txs":0,"uniq":0,"trade":0,"nft":0,"gas":0,"bal":0,"days":0,"spread":0,"streak":0,"rank_m":623030,"pct_m":0.662416},"2023-10":{"txs":0,"uniq":0,"trade":0,"nft":0,"gas":0,"bal":0,"days":0,"spread":0,"streak":0,"rank_m":633647,"pct_m":0.673704},"2023-11":{"txs":0,"uniq":0,"trade":0,"nft":0,"gas":0,"bal":0,"days":0,"spread":0,"streak":0,"rank_m":643063,"pct_m":0.683715},"2023-12":{"txs":0,"uniq":0,"trade":0,"nft":0,"gas":0,"bal":0,"days":0,"spread":0,"streak":0,"rank_m":654398,"pct_m":0.695767},"2024-01":{"txs":0,"uniq":0,"trade":0,"nft":0,"gas":0,"bal":0,"days":0,"spread":0,"streak":0,"rank_m":664499,"pct_m":0.706506},"2024-02":{"txs":0,"uniq":0,"trade":0,"nft":0,"gas":0,"bal":0,"days":0,"spread":0,"streak":0,"rank_m":686275,"pct_m":0.729659},"2024-03":{"txs":0,"uniq":0,"trade":0,"nft":0,"gas":0,"bal":0,"days":0,"spread":0,"streak":0,"rank_m":721648,"pct_m":0.767268},"2024-04":{"txs":0,"uniq":0,"trade":0,"nft":0,"gas":0,"bal":0,"days":0,"spread":0,"streak":0,"rank_m":755493,"pct_m":0.803253},"2024-05":{"txs":0,"uniq":0,"trade":0,"nft":0,"gas":0,"bal":0,"days":0,"spread":0,"streak":0,"rank_m":774053,"pct_m":0.822986},"2024-06":{"txs":0,"uniq":0,"trade":0,"nft":0,"gas":0,"bal":0,"days":0,"spread":0,"streak":0,"rank_m":789910,"pct_m":0.839845},"2024-07":{"txs":0,"uniq":0,"trade":0,"nft":0,"gas":0,"bal":0,"days":0,"spread":0,"streak":0,"rank_m":802917,"pct_m":0.853675},"2024-08":{"txs":0,"uniq":0,"trade":0,"nft":0,"gas":0,"bal":0,"days":0,"spread":0,"streak":0,"rank_m":814047,"pct_m":0.865508},"2024-09":{"txs":0,"uniq":0,"trade":0,"nft":0,"gas":0,"bal":0,"days":0,"spread":0,"streak":0,"rank_m":823122,"pct_m":0.875157},"2024-10":{"txs":0,"uniq":0,"trade":0,"nft":0,"gas":0,"bal":0,"days":0,"spread":0,"streak":0,"rank_m":835405,"pct_m":0.888216},"2024-11":{"txs":0,"uniq":0,"trade":0,"nft":0,"gas":0,"bal":0,"days":0,"spread":0,"streak":0,"rank_m":845916,"pct_m":0.899392},"2024-12":{"txs":0,"uniq":0,"trade":0,"nft":0,"gas":0,"bal":0,"days":0,"spread":0,"streak":0,"rank_m":859782,"pct_m":0.914135},"2025-01":{"txs":0,"uniq":0,"trade":0,"nft":0,"gas":0,"bal":0,"days":0,"spread":0,"streak":0,"rank_m":872028,"pct_m":0.927155},"2025-02":{"txs":0,"uniq":0,"trade":0,"nft":0,"gas":0,"bal":0,"days":0,"spread":0,"streak":0,"rank_m":884947,"pct_m":0.94089},"2025-03":{"txs":0,"uniq":0,"trade":0,"nft":0,"gas":0,"bal":0,"days":0,"spread":0,"streak":0,"rank_m":897131,"pct_m":0.953845},"2025-04":{"txs":0,"uniq":0,"trade":0,"nft":0,"gas":0,"bal":0,"days":0,"spread":0,"streak":0,"rank_m":909895,"pct_m":0.967416},"2025-05":{"txs":11,"uniq":8,"trade":0,"nft":0,"gas":0.000077,"bal":0.000105,"days":2,"spread":0.064516,"streak":1,"rank_m":525180,"pct_m":0.55838,"gas_method":"estimated"},"2025-06":{"txs":50,"uniq":15,"trade":0,"nft":1,"gas":0.000352,"bal":0.004046,"days":12,"spread":0.4,"streak":2,"rank_m":116763,"pct_m":0.124143,"gas_method":"estimated"},"2025-07":{"txs":40,"uniq":7,"trade":0,"nft":0,"gas":0.000282,"bal":0.008453,"days":14,"spread":0.451613,"streak":3,"rank_m":130212,"pct_m":0.138443,"gas_method":"estimated"},"2025-08":{"txs":50,"uniq":9,"trade":0,"nft":0,"gas":0.000352,"bal":0.007055,"days":17,"spread":0.548387,"streak":4,"rank_m":93322,"pct_m":0.099221,"gas_method":"estimated"},"2025-09":{"txs":17,"uniq":5,"trade":0,"nft":0,"gas":0.00012,"bal":0.007175,"days":9,"spread":0.3,"streak":4,"rank_m":174474,"pct_m":0.185503,"gas_method":"estimated"},"2025-10":{"txs":3,"uniq":3,"trade":0,"nft":0,"gas":0.000021,"bal":0.007027,"days":1,"spread":0.032258,"streak":1,"rank_m":228987,"pct_m":0.243462,"gas_method":"estimated"}}}