{"wallet":"0x6aec8504a7d3dcce955010bd49e165392ec53d0c","rank":867814,"lifetime":{"months_active":5,"first":"2023-07","last":"2025-10","tx_sum":227,"uniq_sum":48,"trade_sum":0,"nft_sum":8,"gas_sum":0.001598,"avg_balance_eth_mean":0.000021,"streak_best_days":21,"gas_sum_filled":0.001598},"months":{"2023-07":{"txs":0,"uniq":0,"trade":0,"nft":0,"gas":0,"bal":0,"days":0,"spread":0,"streak":0,"rank_m":568965,"pct_m":0.604933},"2023-08":{"txs":0,"uniq":0,"trade":0,"nft":0,"gas":0,"bal":0,"days":0,"spread":0,"streak":0,"rank_m":617070,"pct_m":0.656079},"2023-09":{"txs":0,"uniq":0,"trade":0,"nft":0,"gas":0,"bal":0,"days":0,"spread":0,"streak":0,"rank_m":629943,"pct_m":0.669766},"2023-10":{"txs":0,"uniq":0,"trade":0,"nft":0,"gas":0,"bal":0,"days":0,"spread":0,"streak":0,"rank_m":640330,"pct_m":0.680809},"2023-11":{"txs":0,"uniq":0,"trade":0,"nft":0,"gas":0,"bal":0,"days":0,"spread":0,"streak":0,"rank_m":649523,"pct_m":0.690583},"2023-12":{"txs":0,"uniq":0,"trade":0,"nft":0,"gas":0,"bal":0,"days":0,"spread":0,"streak":0,"rank_m":660610,"pct_m":0.702371},"2024-01":{"txs":0,"uniq":0,"trade":0,"nft":0,"gas":0,"bal":0,"days":0,"spread":0,"streak":0,"rank_m":670467,"pct_m":0.712851},"2024-02":{"txs":0,"uniq":0,"trade":0,"nft":0,"gas":0,"bal":0,"days":0,"spread":0,"streak":0,"rank_m":691749,"pct_m":0.735479},"2024-03":{"txs":0,"uniq":0,"trade":0,"nft":0,"gas":0,"bal":0,"days":0,"spread":0,"streak":0,"rank_m":726372,"pct_m":0.772291},"2024-04":{"txs":0,"uniq":0,"trade":0,"nft":0,"gas":0,"bal":0,"days":0,"spread":0,"streak":0,"rank_m":759493,"pct_m":0.807505},"2024-05":{"txs":0,"uniq":0,"trade":0,"nft":0,"gas":0,"bal":0,"days":0,"spread":0,"streak":0,"rank_m":777647,"pct_m":0.826807},"2024-06":{"txs":0,"uniq":0,"trade":0,"nft":0,"gas":0,"bal":0,"days":0,"spread":0,"streak":0,"rank_m":793161,"pct_m":0.843302},"2024-07":{"txs":0,"uniq":0,"trade":0,"nft":0,"gas":0,"bal":0,"days":0,"spread":0,"streak":0,"rank_m":805876,"pct_m":0.856821},"2024-08":{"txs":0,"uniq":0,"trade":0,"nft":0,"gas":0,"bal":0,"days":0,"spread":0,"streak":0,"rank_m":816779,"pct_m":0.868413},"2024-09":{"txs":0,"uniq":0,"trade":0,"nft":0,"gas":0,"bal":0,"days":0,"spread":0,"streak":0,"rank_m":825659,"pct_m":0.877854},"2024-10":{"txs":0,"uniq":0,"trade":0,"nft":0,"gas":0,"bal":0,"days":0,"spread":0,"streak":0,"rank_m":837656,"pct_m":0.89061},"2024-11":{"txs":0,"uniq":0,"trade":0,"nft":0,"gas":0,"bal":0,"days":0,"spread":0,"streak":0,"rank_m":847948,"pct_m":0.901552},"2024-12":{"txs":0,"uniq":0,"trade":0,"nft":0,"gas":0,"bal":0,"days":0,"spread":0,"streak":0,"rank_m":861529,"pct_m":0.915992},"2025-01":{"txs":0,"uniq":0,"trade":0,"nft":0,"gas":0,"bal":0,"days":0,"spread":0,"streak":0,"rank_m":873504,"pct_m":0.928724},"2025-02":{"txs":0,"uniq":0,"trade":0,"nft":0,"gas":0,"bal":0,"days":0,"spread":0,"streak":0,"rank_m":886138,"pct_m":0.942157},"2025-03":{"txs":0,"uniq":0,"trade":0,"nft":0,"gas":0,"bal":0,"days":0,"spread":0,"streak":0,"rank_m":898216,"pct_m":0.954998},"2025-04":{"txs":0,"uniq":0,"trade":0,"nft":0,"gas":0,"bal":0,"days":0,"spread":0,"streak":0,"rank_m":910797,"pct_m":0.968375},"2025-05":{"txs":0,"uniq":0,"trade":0,"nft":0,"gas":0,"bal":0,"days":0,"spread":0,"streak":0,"rank_m":918398,"pct_m":0.976456},"2025-06":{"txs":17,"uniq":6,"trade":0,"nft":2,"gas":0.00012,"bal":0.000005,"days":8,"spread":0.266667,"streak":5,"rank_m":414656,"pct_m":0.440869,"gas_method":"estimated"},"2025-07":{"txs":32,"uniq":7,"trade":0,"nft":0,"gas":0.000225,"bal":0.000175,"days":6,"spread":0.193548,"streak":4,"rank_m":438531,"pct_m":0.466253,"gas_method":"estimated"},"2025-08":{"txs":153,"uniq":24,"trade":0,"nft":5,"gas":0.001077,"bal":0.000125,"days":23,"spread":0.741935,"streak":20,"rank_m":198180,"pct_m":0.210707,"gas_method":"estimated"},"2025-09":{"txs":24,"uniq":10,"trade":0,"nft":1,"gas":0.000169,"bal":0.000146,"days":11,"spread":0.366667,"streak":2,"rank_m":314405,"pct_m":0.33428,"gas_method":"estimated"},"2025-10":{"txs":1,"uniq":1,"trade":0,"nft":0,"gas":0.000007,"bal":0.000124,"days":1,"spread":0.032258,"streak":1,"rank_m":519513,"pct_m":0.552354,"gas_method":"estimated"}}}