{"wallet":"0x6060d2952494cb8f043280749b5aa5f86bbfd8ca","rank":406796,"lifetime":{"months_active":16,"first":"2023-07","last":"2025-10","tx_sum":174,"uniq_sum":104,"trade_sum":4,"nft_sum":36,"gas_sum":0.002275,"avg_balance_eth_mean":0.010093,"streak_best_days":3,"gas_sum_filled":0.002275},"months":{"2023-07":{"txs":0,"uniq":0,"trade":0,"nft":0,"gas":0,"bal":0,"days":0,"spread":0,"streak":0,"rank_m":605638,"pct_m":0.643924},"2023-08":{"txs":0,"uniq":0,"trade":0,"nft":0,"gas":0,"bal":0,"days":0,"spread":0,"streak":0,"rank_m":648970,"pct_m":0.689995},"2023-09":{"txs":0,"uniq":0,"trade":0,"nft":0,"gas":0,"bal":0,"days":0,"spread":0,"streak":0,"rank_m":660573,"pct_m":0.702332},"2023-10":{"txs":0,"uniq":0,"trade":0,"nft":0,"gas":0,"bal":0,"days":0,"spread":0,"streak":0,"rank_m":669954,"pct_m":0.712306},"2023-11":{"txs":0,"uniq":0,"trade":0,"nft":0,"gas":0,"bal":0,"days":0,"spread":0,"streak":0,"rank_m":678213,"pct_m":0.721087},"2023-12":{"txs":0,"uniq":0,"trade":0,"nft":0,"gas":0,"bal":0,"days":0,"spread":0,"streak":0,"rank_m":688197,"pct_m":0.731702},"2024-01":{"txs":0,"uniq":0,"trade":0,"nft":0,"gas":0,"bal":0,"days":0,"spread":0,"streak":0,"rank_m":697092,"pct_m":0.74116},"2024-02":{"txs":5,"uniq":4,"trade":0,"nft":0,"gas":0.000065,"bal":0.000836,"days":1,"spread":0.034483,"streak":1,"rank_m":234526,"pct_m":0.249351,"gas_method":"estimated"},"2024-03":{"txs":92,"uniq":43,"trade":0,"nft":6,"gas":0.00178,"bal":0.008162,"days":5,"spread":0.16129,"streak":3,"rank_m":61574,"pct_m":0.065466,"gas_method":"estimated"},"2024-04":{"txs":14,"uniq":8,"trade":0,"nft":3,"gas":0.000033,"bal":0.016563,"days":5,"spread":0.166667,"streak":2,"rank_m":202641,"pct_m":0.21545,"gas_method":"estimated"},"2024-05":{"txs":17,"uniq":13,"trade":0,"nft":6,"gas":0.000013,"bal":0.013383,"days":4,"spread":0.129032,"streak":2,"rank_m":149028,"pct_m":0.158448,"gas_method":"estimated"},"2024-06":{"txs":5,"uniq":4,"trade":0,"nft":3,"gas":0,"bal":0.011043,"days":2,"spread":0.066667,"streak":1,"rank_m":281012,"pct_m":0.298776,"gas_method":"estimated"},"2024-07":{"txs":1,"uniq":1,"trade":0,"nft":0,"gas":0,"bal":0.01104,"days":1,"spread":0.032258,"streak":1,"rank_m":391170,"pct_m":0.415898,"gas_method":"estimated"},"2024-08":{"txs":3,"uniq":2,"trade":0,"nft":1,"gas":0,"bal":0.011482,"days":2,"spread":0.064516,"streak":2,"rank_m":292794,"pct_m":0.311303,"gas_method":"estimated"},"2024-09":{"txs":11,"uniq":10,"trade":0,"nft":12,"gas":0,"bal":0.010973,"days":1,"spread":0.033333,"streak":1,"rank_m":176620,"pct_m":0.187784,"gas_method":"estimated"},"2024-10":{"txs":2,"uniq":2,"trade":0,"nft":2,"gas":0,"bal":0.01125,"days":2,"spread":0.064516,"streak":1,"rank_m":323113,"pct_m":0.343538,"gas_method":"estimated"},"2024-11":{"txs":1,"uniq":1,"trade":0,"nft":1,"gas":0.000002,"bal":0.013176,"days":1,"spread":0.033333,"streak":1,"rank_m":391114,"pct_m":0.415838,"gas_method":"exact"},"2024-12":{"txs":4,"uniq":3,"trade":0,"nft":1,"gas":0.000088,"bal":0.013055,"days":3,"spread":0.096774,"streak":2,"rank_m":330127,"pct_m":0.350996,"gas_method":"exact"},"2025-01":{"txs":9,"uniq":5,"trade":0,"nft":0,"gas":0.000234,"bal":0.013593,"days":1,"spread":0.032258,"streak":1,"rank_m":337917,"pct_m":0.359278,"gas_method":"exact"},"2025-02":{"txs":1,"uniq":1,"trade":0,"nft":1,"gas":0.000007,"bal":0.013972,"days":1,"spread":0.035714,"streak":1,"rank_m":384311,"pct_m":0.408605,"gas_method":"exact"},"2025-03":{"txs":1,"uniq":1,"trade":1,"nft":0,"gas":0.000008,"bal":0.013882,"days":1,"spread":0.032258,"streak":1,"rank_m":348704,"pct_m":0.370747,"gas_method":"exact"},"2025-04":{"txs":5,"uniq":4,"trade":0,"nft":0,"gas":0.000024,"bal":0.01387,"days":1,"spread":0.033333,"streak":1,"rank_m":342580,"pct_m":0.364236,"gas_method":"exact"},"2025-05":{"txs":3,"uniq":2,"trade":3,"nft":0,"gas":0.000021,"bal":0.017723,"days":1,"spread":0.032258,"streak":1,"rank_m":217323,"pct_m":0.231061,"gas_method":"estimated"},"2025-06":{"txs":0,"uniq":0,"trade":0,"nft":0,"gas":0,"bal":0.017723,"days":0,"spread":0,"streak":0,"rank_m":495850,"pct_m":0.527196},"2025-07":{"txs":0,"uniq":0,"trade":0,"nft":0,"gas":0,"bal":0.017723,"days":0,"spread":0,"streak":0,"rank_m":513460,"pct_m":0.545919},"2025-08":{"txs":0,"uniq":0,"trade":0,"nft":0,"gas":0,"bal":0.017723,"days":0,"spread":0,"streak":0,"rank_m":490449,"pct_m":0.521453},"2025-09":{"txs":0,"uniq":0,"trade":0,"nft":0,"gas":0,"bal":0.017723,"days":0,"spread":0,"streak":0,"rank_m":485763,"pct_m":0.516471},"2025-10":{"txs":0,"uniq":0,"trade":0,"nft":0,"gas":0,"bal":0.017723,"days":0,"spread":0,"streak":0,"rank_m":394775,"pct_m":0.419731}}}