{"wallet":"0x6929bca8c786a155742dba13cd3d6e2d70d8d5be","rank":807708,"lifetime":{"months_active":8,"first":"2023-07","last":"2025-10","tx_sum":123,"uniq_sum":45,"trade_sum":1,"nft_sum":0,"gas_sum":0.001074,"avg_balance_eth_mean":0.006436,"streak_best_days":4,"gas_sum_filled":0.001074},"months":{"2023-07":{"txs":0,"uniq":0,"trade":0,"nft":0,"gas":0,"bal":0,"days":0,"spread":0,"streak":0,"rank_m":575184,"pct_m":0.611545},"2023-08":{"txs":0,"uniq":0,"trade":0,"nft":0,"gas":0,"bal":0,"days":0,"spread":0,"streak":0,"rank_m":622462,"pct_m":0.661812},"2023-09":{"txs":0,"uniq":0,"trade":0,"nft":0,"gas":0,"bal":0,"days":0,"spread":0,"streak":0,"rank_m":635119,"pct_m":0.675269},"2023-10":{"txs":0,"uniq":0,"trade":0,"nft":0,"gas":0,"bal":0,"days":0,"spread":0,"streak":0,"rank_m":645329,"pct_m":0.686124},"2023-11":{"txs":0,"uniq":0,"trade":0,"nft":0,"gas":0,"bal":0,"days":0,"spread":0,"streak":0,"rank_m":654375,"pct_m":0.695742},"2023-12":{"txs":0,"uniq":0,"trade":0,"nft":0,"gas":0,"bal":0,"days":0,"spread":0,"streak":0,"rank_m":665298,"pct_m":0.707356},"2024-01":{"txs":0,"uniq":0,"trade":0,"nft":0,"gas":0,"bal":0,"days":0,"spread":0,"streak":0,"rank_m":674989,"pct_m":0.717659},"2024-02":{"txs":4,"uniq":1,"trade":0,"nft":0,"gas":0.000166,"bal":0.000018,"days":1,"spread":0.034483,"streak":1,"rank_m":279450,"pct_m":0.297115,"gas_method":"estimated"},"2024-03":{"txs":0,"uniq":0,"trade":0,"nft":0,"gas":0,"bal":0.000018,"days":0,"spread":0,"streak":0,"rank_m":501986,"pct_m":0.533719},"2024-04":{"txs":0,"uniq":0,"trade":0,"nft":0,"gas":0,"bal":0.000018,"days":0,"spread":0,"streak":0,"rank_m":568823,"pct_m":0.604782},"2024-05":{"txs":0,"uniq":0,"trade":0,"nft":0,"gas":0,"bal":0.000018,"days":0,"spread":0,"streak":0,"rank_m":607162,"pct_m":0.645544},"2024-06":{"txs":0,"uniq":0,"trade":0,"nft":0,"gas":0,"bal":0.000018,"days":0,"spread":0,"streak":0,"rank_m":637658,"pct_m":0.677968},"2024-07":{"txs":0,"uniq":0,"trade":0,"nft":0,"gas":0,"bal":0.000018,"days":0,"spread":0,"streak":0,"rank_m":662520,"pct_m":0.704402},"2024-08":{"txs":1,"uniq":1,"trade":0,"nft":0,"gas":0,"bal":0.001251,"days":1,"spread":0.032258,"streak":1,"rank_m":482195,"pct_m":0.512677,"gas_method":"estimated"},"2024-09":{"txs":0,"uniq":0,"trade":0,"nft":0,"gas":0,"bal":0.001251,"days":0,"spread":0,"streak":0,"rank_m":573808,"pct_m":0.610082},"2024-10":{"txs":0,"uniq":0,"trade":0,"nft":0,"gas":0,"bal":0.001251,"days":0,"spread":0,"streak":0,"rank_m":614456,"pct_m":0.6533},"2024-11":{"txs":0,"uniq":0,"trade":0,"nft":0,"gas":0,"bal":0.001251,"days":0,"spread":0,"streak":0,"rank_m":623690,"pct_m":0.663117},"2024-12":{"txs":4,"uniq":3,"trade":0,"nft":0,"gas":0.000088,"bal":0.002993,"days":1,"spread":0.032258,"streak":1,"rank_m":475340,"pct_m":0.505389,"gas_method":"exact"},"2025-01":{"txs":1,"uniq":1,"trade":0,"nft":0,"gas":0.000026,"bal":0.006562,"days":1,"spread":0.032258,"streak":1,"rank_m":493979,"pct_m":0.525206,"gas_method":"exact"},"2025-02":{"txs":0,"uniq":0,"trade":0,"nft":0,"gas":0,"bal":0.006562,"days":0,"spread":0,"streak":0,"rank_m":616659,"pct_m":0.655642},"2025-03":{"txs":0,"uniq":0,"trade":0,"nft":0,"gas":0,"bal":0.006562,"days":0,"spread":0,"streak":0,"rank_m":601918,"pct_m":0.639969},"2025-04":{"txs":0,"uniq":0,"trade":0,"nft":0,"gas":0,"bal":0.006562,"days":0,"spread":0,"streak":0,"rank_m":633322,"pct_m":0.673358},"2025-05":{"txs":0,"uniq":0,"trade":0,"nft":0,"gas":0,"bal":0.006562,"days":0,"spread":0,"streak":0,"rank_m":572120,"pct_m":0.608287},"2025-06":{"txs":32,"uniq":13,"trade":1,"nft":0,"gas":0.000225,"bal":0.014551,"days":11,"spread":0.366667,"streak":2,"rank_m":66445,"pct_m":0.070644,"gas_method":"estimated"},"2025-07":{"txs":38,"uniq":10,"trade":0,"nft":0,"gas":0.000267,"bal":0.030589,"days":15,"spread":0.483871,"streak":4,"rank_m":41031,"pct_m":0.043624,"gas_method":"estimated"},"2025-08":{"txs":31,"uniq":10,"trade":0,"nft":0,"gas":0.000218,"bal":0.031808,"days":12,"spread":0.387097,"streak":2,"rank_m":52447,"pct_m":0.055762,"gas_method":"estimated"},"2025-09":{"txs":12,"uniq":6,"trade":0,"nft":0,"gas":0.000084,"bal":0.031172,"days":5,"spread":0.166667,"streak":1,"rank_m":147041,"pct_m":0.156336,"gas_method":"estimated"},"2025-10":{"txs":0,"uniq":0,"trade":0,"nft":0,"gas":0,"bal":0.031172,"days":0,"spread":0,"streak":0,"rank_m":352979,"pct_m":0.375293}}}