{"wallet":"0x6b06c3beaff79d9b8d32bd96de07f8e00dbd067b","rank":533986,"lifetime":{"months_active":12,"first":"2023-07","last":"2025-10","tx_sum":233,"uniq_sum":115,"trade_sum":0,"nft_sum":160,"gas_sum":0.000169,"avg_balance_eth_mean":0.000198,"streak_best_days":22,"gas_sum_filled":0.000169},"months":{"2023-07":{"txs":0,"uniq":0,"trade":0,"nft":0,"gas":0,"bal":0,"days":0,"spread":0,"streak":0,"rank_m":568594,"pct_m":0.604538},"2023-08":{"txs":0,"uniq":0,"trade":0,"nft":0,"gas":0,"bal":0,"days":0,"spread":0,"streak":0,"rank_m":616741,"pct_m":0.655729},"2023-09":{"txs":0,"uniq":0,"trade":0,"nft":0,"gas":0,"bal":0,"days":0,"spread":0,"streak":0,"rank_m":629624,"pct_m":0.669426},"2023-10":{"txs":0,"uniq":0,"trade":0,"nft":0,"gas":0,"bal":0,"days":0,"spread":0,"streak":0,"rank_m":640021,"pct_m":0.680481},"2023-11":{"txs":0,"uniq":0,"trade":0,"nft":0,"gas":0,"bal":0,"days":0,"spread":0,"streak":0,"rank_m":649220,"pct_m":0.690261},"2023-12":{"txs":0,"uniq":0,"trade":0,"nft":0,"gas":0,"bal":0,"days":0,"spread":0,"streak":0,"rank_m":660322,"pct_m":0.702065},"2024-01":{"txs":0,"uniq":0,"trade":0,"nft":0,"gas":0,"bal":0,"days":0,"spread":0,"streak":0,"rank_m":670184,"pct_m":0.712551},"2024-02":{"txs":0,"uniq":0,"trade":0,"nft":0,"gas":0,"bal":0,"days":0,"spread":0,"streak":0,"rank_m":691489,"pct_m":0.735202},"2024-03":{"txs":0,"uniq":0,"trade":0,"nft":0,"gas":0,"bal":0,"days":0,"spread":0,"streak":0,"rank_m":726144,"pct_m":0.772048},"2024-04":{"txs":0,"uniq":0,"trade":0,"nft":0,"gas":0,"bal":0,"days":0,"spread":0,"streak":0,"rank_m":759301,"pct_m":0.807301},"2024-05":{"txs":33,"uniq":10,"trade":0,"nft":22,"gas":0.000008,"bal":0.000051,"days":11,"spread":0.354839,"streak":10,"rank_m":224796,"pct_m":0.239006,"gas_method":"estimated"},"2024-06":{"txs":125,"uniq":58,"trade":0,"nft":93,"gas":0.000001,"bal":0.000226,"days":28,"spread":0.933333,"streak":15,"rank_m":56470,"pct_m":0.060039,"gas_method":"exact"},"2024-07":{"txs":43,"uniq":20,"trade":0,"nft":34,"gas":0.000004,"bal":0.000484,"days":21,"spread":0.677419,"streak":10,"rank_m":58764,"pct_m":0.062478,"gas_method":"exact"},"2024-08":{"txs":6,"uniq":4,"trade":0,"nft":4,"gas":0,"bal":0.000587,"days":4,"spread":0.129032,"streak":1,"rank_m":382253,"pct_m":0.406417,"gas_method":"estimated"},"2024-09":{"txs":8,"uniq":5,"trade":0,"nft":7,"gas":0,"bal":0.000918,"days":8,"spread":0.266667,"streak":2,"rank_m":233388,"pct_m":0.248141,"gas_method":"estimated"},"2024-10":{"txs":0,"uniq":0,"trade":0,"nft":0,"gas":0,"bal":0.000918,"days":0,"spread":0,"streak":0,"rank_m":626463,"pct_m":0.666066},"2024-11":{"txs":9,"uniq":9,"trade":0,"nft":0,"gas":0.000021,"bal":0.000141,"days":3,"spread":0.1,"streak":1,"rank_m":371991,"pct_m":0.395506,"gas_method":"exact"},"2024-12":{"txs":1,"uniq":1,"trade":0,"nft":0,"gas":0.000022,"bal":0.000124,"days":1,"spread":0.032258,"streak":1,"rank_m":592197,"pct_m":0.629633,"gas_method":"exact"},"2025-01":{"txs":3,"uniq":3,"trade":0,"nft":0,"gas":0.000078,"bal":0.000396,"days":3,"spread":0.096774,"streak":1,"rank_m":482088,"pct_m":0.512564,"gas_method":"exact"},"2025-02":{"txs":0,"uniq":0,"trade":0,"nft":0,"gas":0,"bal":0.000396,"days":0,"spread":0,"streak":0,"rank_m":725248,"pct_m":0.771096},"2025-03":{"txs":0,"uniq":0,"trade":0,"nft":0,"gas":0,"bal":0.000396,"days":0,"spread":0,"streak":0,"rank_m":735377,"pct_m":0.781865},"2025-04":{"txs":0,"uniq":0,"trade":0,"nft":0,"gas":0,"bal":0.000396,"days":0,"spread":0,"streak":0,"rank_m":757956,"pct_m":0.805871},"2025-05":{"txs":1,"uniq":1,"trade":0,"nft":0,"gas":0.000007,"bal":0.00022,"days":1,"spread":0.032258,"streak":1,"rank_m":622257,"pct_m":0.661594,"gas_method":"estimated"},"2025-06":{"txs":0,"uniq":0,"trade":0,"nft":0,"gas":0,"bal":0.00022,"days":0,"spread":0,"streak":0,"rank_m":793532,"pct_m":0.843696},"2025-07":{"txs":1,"uniq":1,"trade":0,"nft":0,"gas":0.000007,"bal":0.000016,"days":1,"spread":0.032258,"streak":1,"rank_m":708461,"pct_m":0.753247,"gas_method":"estimated"},"2025-08":{"txs":2,"uniq":2,"trade":0,"nft":0,"gas":0.000014,"bal":0.000019,"days":1,"spread":0.032258,"streak":1,"rank_m":671264,"pct_m":0.713699,"gas_method":"estimated"},"2025-09":{"txs":0,"uniq":0,"trade":0,"nft":0,"gas":0,"bal":0.000019,"days":0,"spread":0,"streak":0,"rank_m":892360,"pct_m":0.948772},"2025-10":{"txs":1,"uniq":1,"trade":0,"nft":0,"gas":0.000007,"bal":0.000009,"days":1,"spread":0.032258,"streak":1,"rank_m":581845,"pct_m":0.618627,"gas_method":"estimated"}}}