{"wallet":"0x6b4f2db18ea791a0c4d96f8954457d705d5fdd0a","rank":762414,"lifetime":{"months_active":11,"first":"2023-07","last":"2025-10","tx_sum":145,"uniq_sum":57,"trade_sum":4,"nft_sum":0,"gas_sum":0.001106,"avg_balance_eth_mean":0.001021,"streak_best_days":4,"gas_sum_filled":0.001106},"months":{"2023-07":{"txs":0,"uniq":0,"trade":0,"nft":0,"gas":0,"bal":0,"days":0,"spread":0,"streak":0,"rank_m":567608,"pct_m":0.60349},"2023-08":{"txs":0,"uniq":0,"trade":0,"nft":0,"gas":0,"bal":0,"days":0,"spread":0,"streak":0,"rank_m":615881,"pct_m":0.654815},"2023-09":{"txs":0,"uniq":0,"trade":0,"nft":0,"gas":0,"bal":0,"days":0,"spread":0,"streak":0,"rank_m":628806,"pct_m":0.668557},"2023-10":{"txs":0,"uniq":0,"trade":0,"nft":0,"gas":0,"bal":0,"days":0,"spread":0,"streak":0,"rank_m":639232,"pct_m":0.679642},"2023-11":{"txs":0,"uniq":0,"trade":0,"nft":0,"gas":0,"bal":0,"days":0,"spread":0,"streak":0,"rank_m":648466,"pct_m":0.68946},"2023-12":{"txs":0,"uniq":0,"trade":0,"nft":0,"gas":0,"bal":0,"days":0,"spread":0,"streak":0,"rank_m":659593,"pct_m":0.70129},"2024-01":{"txs":0,"uniq":0,"trade":0,"nft":0,"gas":0,"bal":0,"days":0,"spread":0,"streak":0,"rank_m":669481,"pct_m":0.711803},"2024-02":{"txs":0,"uniq":0,"trade":0,"nft":0,"gas":0,"bal":0,"days":0,"spread":0,"streak":0,"rank_m":690839,"pct_m":0.734511},"2024-03":{"txs":0,"uniq":0,"trade":0,"nft":0,"gas":0,"bal":0,"days":0,"spread":0,"streak":0,"rank_m":725572,"pct_m":0.77144},"2024-04":{"txs":0,"uniq":0,"trade":0,"nft":0,"gas":0,"bal":0,"days":0,"spread":0,"streak":0,"rank_m":758820,"pct_m":0.80679},"2024-05":{"txs":0,"uniq":0,"trade":0,"nft":0,"gas":0,"bal":0,"days":0,"spread":0,"streak":0,"rank_m":777043,"pct_m":0.826165},"2024-06":{"txs":0,"uniq":0,"trade":0,"nft":0,"gas":0,"bal":0,"days":0,"spread":0,"streak":0,"rank_m":792608,"pct_m":0.842714},"2024-07":{"txs":0,"uniq":0,"trade":0,"nft":0,"gas":0,"bal":0,"days":0,"spread":0,"streak":0,"rank_m":805371,"pct_m":0.856284},"2024-08":{"txs":0,"uniq":0,"trade":0,"nft":0,"gas":0,"bal":0,"days":0,"spread":0,"streak":0,"rank_m":816312,"pct_m":0.867916},"2024-09":{"txs":0,"uniq":0,"trade":0,"nft":0,"gas":0,"bal":0,"days":0,"spread":0,"streak":0,"rank_m":825216,"pct_m":0.877383},"2024-10":{"txs":0,"uniq":0,"trade":0,"nft":0,"gas":0,"bal":0,"days":0,"spread":0,"streak":0,"rank_m":837256,"pct_m":0.890184},"2024-11":{"txs":0,"uniq":0,"trade":0,"nft":0,"gas":0,"bal":0,"days":0,"spread":0,"streak":0,"rank_m":847595,"pct_m":0.901177},"2024-12":{"txs":5,"uniq":4,"trade":0,"nft":0,"gas":0.000088,"bal":0.000431,"days":4,"spread":0.129032,"streak":2,"rank_m":440665,"pct_m":0.468522,"gas_method":"exact"},"2025-01":{"txs":2,"uniq":2,"trade":0,"nft":0,"gas":0.000052,"bal":0.002156,"days":2,"spread":0.064516,"streak":1,"rank_m":477285,"pct_m":0.507457,"gas_method":"exact"},"2025-02":{"txs":1,"uniq":1,"trade":0,"nft":0,"gas":0.000007,"bal":0.002154,"days":1,"spread":0.035714,"streak":1,"rank_m":488918,"pct_m":0.519825,"gas_method":"exact"},"2025-03":{"txs":2,"uniq":2,"trade":1,"nft":0,"gas":0.000016,"bal":0.002113,"days":2,"spread":0.064516,"streak":1,"rank_m":356270,"pct_m":0.378792,"gas_method":"exact"},"2025-04":{"txs":7,"uniq":4,"trade":1,"nft":0,"gas":0.000042,"bal":0.001879,"days":7,"spread":0.233333,"streak":4,"rank_m":192684,"pct_m":0.204864,"gas_method":"exact"},"2025-05":{"txs":8,"uniq":5,"trade":0,"nft":0,"gas":0.000056,"bal":0.001491,"days":7,"spread":0.225806,"streak":2,"rank_m":281672,"pct_m":0.299478,"gas_method":"estimated"},"2025-06":{"txs":22,"uniq":7,"trade":2,"nft":0,"gas":0.000155,"bal":0.002558,"days":9,"spread":0.3,"streak":2,"rank_m":202927,"pct_m":0.215755,"gas_method":"estimated"},"2025-07":{"txs":23,"uniq":11,"trade":0,"nft":0,"gas":0.000162,"bal":0.002792,"days":9,"spread":0.290323,"streak":3,"rank_m":242377,"pct_m":0.257698,"gas_method":"estimated"},"2025-08":{"txs":27,"uniq":12,"trade":0,"nft":0,"gas":0.00019,"bal":0.00398,"days":13,"spread":0.419355,"streak":3,"rank_m":171819,"pct_m":0.18268,"gas_method":"estimated"},"2025-09":{"txs":24,"uniq":8,"trade":0,"nft":0,"gas":0.000169,"bal":0.004486,"days":13,"spread":0.433333,"streak":3,"rank_m":174627,"pct_m":0.185665,"gas_method":"estimated"},"2025-10":{"txs":24,"uniq":1,"trade":0,"nft":0,"gas":0.000169,"bal":0.004543,"days":8,"spread":0.258065,"streak":2,"rank_m":169292,"pct_m":0.179993,"gas_method":"estimated"}}}