{"wallet":"0x6cdd675a2abd2d56e52ae007839e47c1e21926d3","rank":356587,"lifetime":{"months_active":15,"first":"2023-07","last":"2025-10","tx_sum":528,"uniq_sum":224,"trade_sum":0,"nft_sum":276,"gas_sum":0.000382,"avg_balance_eth_mean":0.000022,"streak_best_days":31,"gas_sum_filled":0.000382},"months":{"2023-07":{"txs":0,"uniq":0,"trade":0,"nft":0,"gas":0,"bal":0,"days":0,"spread":0,"streak":0,"rank_m":562296,"pct_m":0.597842},"2023-08":{"txs":0,"uniq":0,"trade":0,"nft":0,"gas":0,"bal":0,"days":0,"spread":0,"streak":0,"rank_m":611284,"pct_m":0.649927},"2023-09":{"txs":0,"uniq":0,"trade":0,"nft":0,"gas":0,"bal":0,"days":0,"spread":0,"streak":0,"rank_m":624389,"pct_m":0.66386},"2023-10":{"txs":0,"uniq":0,"trade":0,"nft":0,"gas":0,"bal":0,"days":0,"spread":0,"streak":0,"rank_m":634959,"pct_m":0.675099},"2023-11":{"txs":0,"uniq":0,"trade":0,"nft":0,"gas":0,"bal":0,"days":0,"spread":0,"streak":0,"rank_m":644337,"pct_m":0.68507},"2023-12":{"txs":0,"uniq":0,"trade":0,"nft":0,"gas":0,"bal":0,"days":0,"spread":0,"streak":0,"rank_m":655614,"pct_m":0.697059},"2024-01":{"txs":0,"uniq":0,"trade":0,"nft":0,"gas":0,"bal":0,"days":0,"spread":0,"streak":0,"rank_m":665664,"pct_m":0.707745},"2024-02":{"txs":0,"uniq":0,"trade":0,"nft":0,"gas":0,"bal":0,"days":0,"spread":0,"streak":0,"rank_m":687354,"pct_m":0.730806},"2024-03":{"txs":0,"uniq":0,"trade":0,"nft":0,"gas":0,"bal":0,"days":0,"spread":0,"streak":0,"rank_m":722575,"pct_m":0.768254},"2024-04":{"txs":0,"uniq":0,"trade":0,"nft":0,"gas":0,"bal":0,"days":0,"spread":0,"streak":0,"rank_m":756267,"pct_m":0.804076},"2024-05":{"txs":26,"uniq":10,"trade":0,"nft":15,"gas":0.000017,"bal":0.000008,"days":5,"spread":0.16129,"streak":5,"rank_m":276793,"pct_m":0.29429,"gas_method":"estimated"},"2024-06":{"txs":281,"uniq":99,"trade":0,"nft":137,"gas":0.000001,"bal":0.000062,"days":29,"spread":0.966667,"streak":19,"rank_m":60254,"pct_m":0.064062,"gas_method":"exact"},"2024-07":{"txs":149,"uniq":68,"trade":0,"nft":84,"gas":0.000011,"bal":0.000065,"days":29,"spread":0.935484,"streak":21,"rank_m":47614,"pct_m":0.050623,"gas_method":"exact"},"2024-08":{"txs":24,"uniq":16,"trade":0,"nft":21,"gas":0.000002,"bal":0.000042,"days":18,"spread":0.580645,"streak":5,"rank_m":231385,"pct_m":0.246012,"gas_method":"estimated"},"2024-09":{"txs":15,"uniq":8,"trade":0,"nft":12,"gas":0,"bal":0.000022,"days":10,"spread":0.333333,"streak":2,"rank_m":268241,"pct_m":0.285198,"gas_method":"estimated"},"2024-10":{"txs":6,"uniq":3,"trade":0,"nft":5,"gas":0,"bal":0.000013,"days":6,"spread":0.193548,"streak":2,"rank_m":405434,"pct_m":0.431064,"gas_method":"estimated"},"2024-11":{"txs":1,"uniq":1,"trade":0,"nft":0,"gas":0.000002,"bal":0.00001,"days":1,"spread":0.033333,"streak":1,"rank_m":536601,"pct_m":0.570523,"gas_method":"exact"},"2024-12":{"txs":8,"uniq":7,"trade":0,"nft":0,"gas":0.000154,"bal":0.000053,"days":4,"spread":0.129032,"streak":1,"rank_m":442899,"pct_m":0.470897,"gas_method":"exact"},"2025-01":{"txs":5,"uniq":3,"trade":0,"nft":0,"gas":0.000104,"bal":0.00003,"days":2,"spread":0.064516,"streak":1,"rank_m":504887,"pct_m":0.536804,"gas_method":"exact"},"2025-02":{"txs":0,"uniq":0,"trade":0,"nft":0,"gas":0,"bal":0.00003,"days":0,"spread":0,"streak":0,"rank_m":798100,"pct_m":0.848553},"2025-03":{"txs":1,"uniq":1,"trade":0,"nft":0,"gas":0.000008,"bal":0.000043,"days":1,"spread":0.032258,"streak":1,"rank_m":542016,"pct_m":0.57628,"gas_method":"exact"},"2025-04":{"txs":1,"uniq":1,"trade":0,"nft":0,"gas":0.000006,"bal":0.000039,"days":1,"spread":0.033333,"streak":1,"rank_m":582833,"pct_m":0.619677,"gas_method":"exact"},"2025-05":{"txs":1,"uniq":1,"trade":0,"nft":0,"gas":0.000007,"bal":0.000039,"days":1,"spread":0.032258,"streak":1,"rank_m":681921,"pct_m":0.72503,"gas_method":"estimated"},"2025-06":{"txs":0,"uniq":0,"trade":0,"nft":0,"gas":0,"bal":0.000039,"days":0,"spread":0,"streak":0,"rank_m":868248,"pct_m":0.923136},"2025-07":{"txs":7,"uniq":3,"trade":0,"nft":2,"gas":0.000049,"bal":0.000037,"days":3,"spread":0.096774,"streak":1,"rank_m":518350,"pct_m":0.551118,"gas_method":"estimated"},"2025-08":{"txs":2,"uniq":2,"trade":0,"nft":0,"gas":0.000014,"bal":0.000032,"days":2,"spread":0.064516,"streak":1,"rank_m":647745,"pct_m":0.688693,"gas_method":"estimated"},"2025-09":{"txs":0,"uniq":0,"trade":0,"nft":0,"gas":0,"bal":0.000032,"days":0,"spread":0,"streak":0,"rank_m":883035,"pct_m":0.938858},"2025-10":{"txs":1,"uniq":1,"trade":0,"nft":0,"gas":0.000007,"bal":0.000032,"days":1,"spread":0.032258,"streak":1,"rank_m":563507,"pct_m":0.59913,"gas_method":"estimated"}}}