{"wallet":"0x6118983ec1b991098937c46e5814683673845641","rank":495289,"lifetime":{"months_active":22,"first":"2023-07","last":"2025-10","tx_sum":136,"uniq_sum":105,"trade_sum":14,"nft_sum":35,"gas_sum":0.001231,"avg_balance_eth_mean":0.000548,"streak_best_days":2,"gas_sum_filled":0.001231},"months":{"2023-07":{"txs":0,"uniq":0,"trade":0,"nft":0,"gas":0,"bal":0,"days":0,"spread":0,"streak":0,"rank_m":603175,"pct_m":0.641305},"2023-08":{"txs":16,"uniq":10,"trade":1,"nft":7,"gas":0.000222,"bal":0.000368,"days":2,"spread":0.064516,"streak":1,"rank_m":94898,"pct_m":0.100896,"gas_method":"exact"},"2023-09":{"txs":7,"uniq":6,"trade":3,"nft":3,"gas":0.000035,"bal":0.000358,"days":2,"spread":0.066667,"streak":1,"rank_m":81696,"pct_m":0.08686,"gas_method":"exact"},"2023-10":{"txs":3,"uniq":3,"trade":0,"nft":4,"gas":0.000022,"bal":0.000087,"days":1,"spread":0.032258,"streak":1,"rank_m":131276,"pct_m":0.139574,"gas_method":"estimated"},"2023-11":{"txs":2,"uniq":2,"trade":1,"nft":0,"gas":0.000026,"bal":0.000057,"days":1,"spread":0.033333,"streak":1,"rank_m":137662,"pct_m":0.146364,"gas_method":"estimated"},"2023-12":{"txs":4,"uniq":3,"trade":0,"nft":2,"gas":0.000096,"bal":0.000023,"days":1,"spread":0.032258,"streak":1,"rank_m":167730,"pct_m":0.178332,"gas_method":"estimated"},"2024-01":{"txs":2,"uniq":2,"trade":0,"nft":0,"gas":0.000045,"bal":0.000103,"days":1,"spread":0.032258,"streak":1,"rank_m":197720,"pct_m":0.210218,"gas_method":"estimated"},"2024-02":{"txs":0,"uniq":0,"trade":0,"nft":0,"gas":0,"bal":0.000103,"days":0,"spread":0,"streak":0,"rank_m":422453,"pct_m":0.449159},"2024-03":{"txs":9,"uniq":8,"trade":4,"nft":4,"gas":0.00017,"bal":0.000287,"days":1,"spread":0.032258,"streak":1,"rank_m":273804,"pct_m":0.291112,"gas_method":"estimated"},"2024-04":{"txs":2,"uniq":1,"trade":0,"nft":0,"gas":0.000005,"bal":0.000602,"days":1,"spread":0.033333,"streak":1,"rank_m":450976,"pct_m":0.479485,"gas_method":"estimated"},"2024-05":{"txs":6,"uniq":5,"trade":0,"nft":6,"gas":0.000005,"bal":0.000677,"days":3,"spread":0.096774,"streak":1,"rank_m":371120,"pct_m":0.39458,"gas_method":"estimated"},"2024-06":{"txs":0,"uniq":0,"trade":0,"nft":0,"gas":0,"bal":0.000677,"days":0,"spread":0,"streak":0,"rank_m":577993,"pct_m":0.614531},"2024-07":{"txs":2,"uniq":1,"trade":0,"nft":1,"gas":0,"bal":0.001067,"days":1,"spread":0.032258,"streak":1,"rank_m":444631,"pct_m":0.472739,"gas_method":"estimated"},"2024-08":{"txs":12,"uniq":8,"trade":1,"nft":4,"gas":0.000001,"bal":0.000921,"days":4,"spread":0.129032,"streak":2,"rank_m":266727,"pct_m":0.283588,"gas_method":"estimated"},"2024-09":{"txs":3,"uniq":2,"trade":0,"nft":0,"gas":0,"bal":0.000541,"days":1,"spread":0.033333,"streak":1,"rank_m":460196,"pct_m":0.489288,"gas_method":"estimated"},"2024-10":{"txs":2,"uniq":2,"trade":0,"nft":3,"gas":0,"bal":0.000573,"days":1,"spread":0.032258,"streak":1,"rank_m":455823,"pct_m":0.484638,"gas_method":"estimated"},"2024-11":{"txs":6,"uniq":5,"trade":0,"nft":0,"gas":0.000011,"bal":0.000554,"days":2,"spread":0.066667,"streak":1,"rank_m":412729,"pct_m":0.43882,"gas_method":"exact"},"2024-12":{"txs":5,"uniq":4,"trade":3,"nft":0,"gas":0.00011,"bal":0.002583,"days":1,"spread":0.032258,"streak":1,"rank_m":396960,"pct_m":0.422054,"gas_method":"exact"},"2025-01":{"txs":8,"uniq":5,"trade":0,"nft":0,"gas":0.000156,"bal":0.002333,"days":3,"spread":0.096774,"streak":2,"rank_m":343923,"pct_m":0.365664,"gas_method":"exact"},"2025-02":{"txs":15,"uniq":12,"trade":1,"nft":0,"gas":0.000099,"bal":0.000688,"days":5,"spread":0.178571,"streak":1,"rank_m":211716,"pct_m":0.225099,"gas_method":"exact"},"2025-03":{"txs":13,"uniq":9,"trade":0,"nft":1,"gas":0.000095,"bal":0.000408,"days":2,"spread":0.064516,"streak":1,"rank_m":295159,"pct_m":0.313817,"gas_method":"exact"},"2025-04":{"txs":0,"uniq":0,"trade":0,"nft":0,"gas":0,"bal":0.000408,"days":0,"spread":0,"streak":0,"rank_m":761154,"pct_m":0.809271},"2025-05":{"txs":7,"uniq":5,"trade":0,"nft":0,"gas":0.000049,"bal":0.000439,"days":2,"spread":0.064516,"streak":1,"rank_m":475507,"pct_m":0.505566,"gas_method":"estimated"},"2025-06":{"txs":5,"uniq":5,"trade":0,"nft":0,"gas":0.000035,"bal":0.000334,"days":1,"spread":0.033333,"streak":1,"rank_m":555908,"pct_m":0.59105,"gas_method":"estimated"},"2025-07":{"txs":0,"uniq":0,"trade":0,"nft":0,"gas":0,"bal":0.000334,"days":0,"spread":0,"streak":0,"rank_m":796801,"pct_m":0.847172},"2025-08":{"txs":6,"uniq":6,"trade":0,"nft":0,"gas":0.000042,"bal":0.000205,"days":2,"spread":0.064516,"streak":1,"rank_m":538873,"pct_m":0.572938,"gas_method":"estimated"},"2025-09":{"txs":1,"uniq":1,"trade":0,"nft":0,"gas":0.000007,"bal":0.000302,"days":1,"spread":0.033333,"streak":1,"rank_m":582212,"pct_m":0.619017,"gas_method":"estimated"},"2025-10":{"txs":0,"uniq":0,"trade":0,"nft":0,"gas":0,"bal":0.000302,"days":0,"spread":0,"streak":0,"rank_m":726459,"pct_m":0.772383}}}