{"wallet":"0x616c6df365fa1e2dcd8feca56e36efa80cefa129","rank":71014,"lifetime":{"months_active":12,"first":"2023-07","last":"2025-10","tx_sum":1071,"uniq_sum":180,"trade_sum":1,"nft_sum":4,"gas_sum":0.031653,"avg_balance_eth_mean":0.508072,"streak_best_days":16,"gas_sum_filled":0.031653},"months":{"2023-07":{"txs":0,"uniq":0,"trade":0,"nft":0,"gas":0,"bal":0,"days":0,"spread":0,"streak":0,"rank_m":602064,"pct_m":0.640124},"2023-08":{"txs":0,"uniq":0,"trade":0,"nft":0,"gas":0,"bal":0,"days":0,"spread":0,"streak":0,"rank_m":645855,"pct_m":0.686684},"2023-09":{"txs":0,"uniq":0,"trade":0,"nft":0,"gas":0,"bal":0,"days":0,"spread":0,"streak":0,"rank_m":657593,"pct_m":0.699164},"2023-10":{"txs":0,"uniq":0,"trade":0,"nft":0,"gas":0,"bal":0,"days":0,"spread":0,"streak":0,"rank_m":667080,"pct_m":0.70925},"2023-11":{"txs":0,"uniq":0,"trade":0,"nft":0,"gas":0,"bal":0,"days":0,"spread":0,"streak":0,"rank_m":675410,"pct_m":0.718107},"2023-12":{"txs":0,"uniq":0,"trade":0,"nft":0,"gas":0,"bal":0,"days":0,"spread":0,"streak":0,"rank_m":685507,"pct_m":0.728842},"2024-01":{"txs":0,"uniq":0,"trade":0,"nft":0,"gas":0,"bal":0,"days":0,"spread":0,"streak":0,"rank_m":694482,"pct_m":0.738385},"2024-02":{"txs":0,"uniq":0,"trade":0,"nft":0,"gas":0,"bal":0,"days":0,"spread":0,"streak":0,"rank_m":713853,"pct_m":0.75898},"2024-03":{"txs":0,"uniq":0,"trade":0,"nft":0,"gas":0,"bal":0,"days":0,"spread":0,"streak":0,"rank_m":745408,"pct_m":0.79253},"2024-04":{"txs":0,"uniq":0,"trade":0,"nft":0,"gas":0,"bal":0,"days":0,"spread":0,"streak":0,"rank_m":775598,"pct_m":0.824629},"2024-05":{"txs":51,"uniq":9,"trade":0,"nft":0,"gas":0.00013,"bal":0.76776,"days":3,"spread":0.096774,"streak":3,"rank_m":121142,"pct_m":0.128799,"gas_method":"estimated"},"2024-06":{"txs":116,"uniq":13,"trade":0,"nft":1,"gas":0.000011,"bal":3.945165,"days":7,"spread":0.233333,"streak":2,"rank_m":52402,"pct_m":0.055714,"gas_method":"estimated"},"2024-07":{"txs":563,"uniq":65,"trade":0,"nft":1,"gas":0.025585,"bal":2.227676,"days":22,"spread":0.709677,"streak":15,"rank_m":3322,"pct_m":0.003531,"gas_method":"exact"},"2024-08":{"txs":73,"uniq":13,"trade":0,"nft":0,"gas":0.002667,"bal":1.311007,"days":12,"spread":0.387097,"streak":4,"rank_m":26787,"pct_m":0.028479,"gas_method":"exact"},"2024-09":{"txs":9,"uniq":4,"trade":0,"nft":0,"gas":0.000001,"bal":1.106241,"days":2,"spread":0.066667,"streak":1,"rank_m":177262,"pct_m":0.188467,"gas_method":"estimated"},"2024-10":{"txs":4,"uniq":3,"trade":0,"nft":2,"gas":0.000001,"bal":0.581967,"days":2,"spread":0.064516,"streak":1,"rank_m":231825,"pct_m":0.246479,"gas_method":"estimated"},"2024-11":{"txs":63,"uniq":19,"trade":1,"nft":0,"gas":0.000143,"bal":0.334353,"days":3,"spread":0.1,"streak":3,"rank_m":46222,"pct_m":0.049143,"gas_method":"exact"},"2024-12":{"txs":72,"uniq":19,"trade":0,"nft":0,"gas":0.001588,"bal":1.180837,"days":17,"spread":0.548387,"streak":6,"rank_m":26205,"pct_m":0.027861,"gas_method":"exact"},"2025-01":{"txs":36,"uniq":11,"trade":0,"nft":0,"gas":0.000935,"bal":1.152963,"days":10,"spread":0.322581,"streak":3,"rank_m":54639,"pct_m":0.058092,"gas_method":"exact"},"2025-02":{"txs":67,"uniq":13,"trade":0,"nft":0,"gas":0.000472,"bal":0.528975,"days":10,"spread":0.357143,"streak":4,"rank_m":17335,"pct_m":0.01843,"gas_method":"exact"},"2025-03":{"txs":0,"uniq":0,"trade":0,"nft":0,"gas":0,"bal":0.528975,"days":0,"spread":0,"streak":0,"rank_m":509801,"pct_m":0.542028},"2025-04":{"txs":0,"uniq":0,"trade":0,"nft":0,"gas":0,"bal":0.528975,"days":0,"spread":0,"streak":0,"rank_m":548848,"pct_m":0.583544},"2025-05":{"txs":14,"uniq":8,"trade":0,"nft":0,"gas":0.000099,"bal":0.007282,"days":1,"spread":0.032258,"streak":1,"rank_m":231785,"pct_m":0.246437,"gas_method":"estimated"},"2025-06":{"txs":0,"uniq":0,"trade":0,"nft":0,"gas":0,"bal":0.007282,"days":0,"spread":0,"streak":0,"rank_m":567411,"pct_m":0.60328},"2025-07":{"txs":0,"uniq":0,"trade":0,"nft":0,"gas":0,"bal":0.007282,"days":0,"spread":0,"streak":0,"rank_m":585921,"pct_m":0.622961},"2025-08":{"txs":0,"uniq":0,"trade":0,"nft":0,"gas":0,"bal":0.007282,"days":0,"spread":0,"streak":0,"rank_m":565313,"pct_m":0.60105},"2025-09":{"txs":3,"uniq":3,"trade":0,"nft":0,"gas":0.000021,"bal":0.000998,"days":1,"spread":0.033333,"streak":1,"rank_m":484618,"pct_m":0.515253,"gas_method":"estimated"},"2025-10":{"txs":0,"uniq":0,"trade":0,"nft":0,"gas":0,"bal":0.000998,"days":0,"spread":0,"streak":0,"rank_m":631183,"pct_m":0.671084}}}