{"wallet":"0x642aeeaf5682bd88ea22600a420dfec324c748f2","rank":423218,"lifetime":{"months_active":12,"first":"2023-07","last":"2025-10","tx_sum":324,"uniq_sum":138,"trade_sum":3,"nft_sum":4,"gas_sum":0.003706,"avg_balance_eth_mean":0.000097,"streak_best_days":4,"gas_sum_filled":0.003706},"months":{"2023-07":{"txs":0,"uniq":0,"trade":0,"nft":0,"gas":0,"bal":0,"days":0,"spread":0,"streak":0,"rank_m":592694,"pct_m":0.630162},"2023-08":{"txs":0,"uniq":0,"trade":0,"nft":0,"gas":0,"bal":0,"days":0,"spread":0,"streak":0,"rank_m":637672,"pct_m":0.677983},"2023-09":{"txs":0,"uniq":0,"trade":0,"nft":0,"gas":0,"bal":0,"days":0,"spread":0,"streak":0,"rank_m":649731,"pct_m":0.690805},"2023-10":{"txs":0,"uniq":0,"trade":0,"nft":0,"gas":0,"bal":0,"days":0,"spread":0,"streak":0,"rank_m":659475,"pct_m":0.701165},"2023-11":{"txs":0,"uniq":0,"trade":0,"nft":0,"gas":0,"bal":0,"days":0,"spread":0,"streak":0,"rank_m":668042,"pct_m":0.710273},"2023-12":{"txs":0,"uniq":0,"trade":0,"nft":0,"gas":0,"bal":0,"days":0,"spread":0,"streak":0,"rank_m":678427,"pct_m":0.721315},"2024-01":{"txs":0,"uniq":0,"trade":0,"nft":0,"gas":0,"bal":0,"days":0,"spread":0,"streak":0,"rank_m":687663,"pct_m":0.731135},"2024-02":{"txs":0,"uniq":0,"trade":0,"nft":0,"gas":0,"bal":0,"days":0,"spread":0,"streak":0,"rank_m":707589,"pct_m":0.75232},"2024-03":{"txs":0,"uniq":0,"trade":0,"nft":0,"gas":0,"bal":0,"days":0,"spread":0,"streak":0,"rank_m":739980,"pct_m":0.786759},"2024-04":{"txs":0,"uniq":0,"trade":0,"nft":0,"gas":0,"bal":0,"days":0,"spread":0,"streak":0,"rank_m":771020,"pct_m":0.819761},"2024-05":{"txs":0,"uniq":0,"trade":0,"nft":0,"gas":0,"bal":0,"days":0,"spread":0,"streak":0,"rank_m":788041,"pct_m":0.837858},"2024-06":{"txs":1,"uniq":1,"trade":0,"nft":1,"gas":0,"bal":0,"days":1,"spread":0.033333,"streak":1,"rank_m":501612,"pct_m":0.533322,"gas_method":"estimated"},"2024-07":{"txs":0,"uniq":0,"trade":0,"nft":0,"gas":0,"bal":0,"days":0,"spread":0,"streak":0,"rank_m":679659,"pct_m":0.722625},"2024-08":{"txs":0,"uniq":0,"trade":0,"nft":0,"gas":0,"bal":0,"days":0,"spread":0,"streak":0,"rank_m":702726,"pct_m":0.74715},"2024-09":{"txs":0,"uniq":0,"trade":0,"nft":0,"gas":0,"bal":0,"days":0,"spread":0,"streak":0,"rank_m":723688,"pct_m":0.769437},"2024-10":{"txs":0,"uniq":0,"trade":0,"nft":0,"gas":0,"bal":0,"days":0,"spread":0,"streak":0,"rank_m":746976,"pct_m":0.794197},"2024-11":{"txs":2,"uniq":2,"trade":0,"nft":0,"gas":0.000005,"bal":0,"days":1,"spread":0.033333,"streak":1,"rank_m":516942,"pct_m":0.549621,"gas_method":"exact"},"2024-12":{"txs":0,"uniq":0,"trade":0,"nft":0,"gas":0,"bal":0,"days":0,"spread":0,"streak":0,"rank_m":789261,"pct_m":0.839155},"2025-01":{"txs":85,"uniq":26,"trade":0,"nft":0,"gas":0.002052,"bal":0,"days":5,"spread":0.16129,"streak":4,"rank_m":203040,"pct_m":0.215875,"gas_method":"exact"},"2025-02":{"txs":79,"uniq":19,"trade":0,"nft":3,"gas":0.000521,"bal":0.000464,"days":7,"spread":0.25,"streak":3,"rank_m":107314,"pct_m":0.114097,"gas_method":"exact"},"2025-03":{"txs":45,"uniq":21,"trade":0,"nft":0,"gas":0.00034,"bal":0.000582,"days":10,"spread":0.322581,"streak":1,"rank_m":164758,"pct_m":0.175173,"gas_method":"exact"},"2025-04":{"txs":1,"uniq":0,"trade":0,"nft":0,"gas":0.000006,"bal":0.000002,"days":1,"spread":0.033333,"streak":1,"rank_m":719880,"pct_m":0.765388,"gas_method":"estimated"},"2025-05":{"txs":26,"uniq":20,"trade":0,"nft":0,"gas":0.000183,"bal":0.000145,"days":5,"spread":0.16129,"streak":2,"rank_m":396639,"pct_m":0.421713,"gas_method":"estimated"},"2025-06":{"txs":16,"uniq":10,"trade":2,"nft":0,"gas":0.000113,"bal":0.000444,"days":5,"spread":0.166667,"streak":2,"rank_m":322619,"pct_m":0.343013,"gas_method":"estimated"},"2025-07":{"txs":28,"uniq":13,"trade":1,"nft":0,"gas":0.000197,"bal":0.000139,"days":6,"spread":0.193548,"streak":2,"rank_m":334053,"pct_m":0.35517,"gas_method":"estimated"},"2025-08":{"txs":16,"uniq":10,"trade":0,"nft":0,"gas":0.000113,"bal":0.000199,"days":3,"spread":0.096774,"streak":2,"rank_m":457590,"pct_m":0.486517,"gas_method":"estimated"},"2025-09":{"txs":15,"uniq":8,"trade":0,"nft":0,"gas":0.000106,"bal":0.000089,"days":5,"spread":0.166667,"streak":1,"rank_m":505926,"pct_m":0.537909,"gas_method":"estimated"},"2025-10":{"txs":10,"uniq":8,"trade":0,"nft":0,"gas":0.00007,"bal":0.000642,"days":2,"spread":0.064516,"streak":1,"rank_m":314078,"pct_m":0.333932,"gas_method":"estimated"}}}